custom_url_avatar/__init__.py
custom_url_avatar/admin_urls.py
custom_url_avatar/extension.py
custom_url_avatar/forms.py
rbCustomUrlAvatar-1.1.0.dist-info/LICENSE
rbCustomUrlAvatar-1.1.0.dist-info/METADATA
rbCustomUrlAvatar-1.1.0.dist-info/WHEEL
rbCustomUrlAvatar-1.1.0.dist-info/entry_points.txt
rbCustomUrlAvatar-1.1.0.dist-info/top_level.txt
rbCustomUrlAvatar-1.1.0.dist-info/RECORD
