Metadata-Version: 2.1
Name: rbCustomUrlAvatar
Version: 1.1.0
Summary: Review Board extension: CustomUrlAvatar
Home-page: https://github.com/misery/CustomUrlAvatar
Author: Andre Klitzing
Author-email: aklitzing@gmail.com
Classifier: Development Status :: 5 - Production/Stable
Classifier: Framework :: Review Board
Classifier: Intended Audience :: Developers
Classifier: License :: OSI Approved :: MIT License
Classifier: Natural Language :: English
Classifier: Operating System :: OS Independent
Classifier: Programming Language :: Python
License-File: LICENSE
Requires-Dist: reviewboard >=6.0
